event_source/__init__.py
event_source-0.1.0a2.dist-info/LICENSE
event_source-0.1.0a2.dist-info/WHEEL
event_source-0.1.0a2.dist-info/METADATA
event_source-0.1.0a2.dist-info/RECORD
